investimentos/__init__.py
investimentos/investimentos.py
GHPModuleInvest-0.1.dist-info/LICENSE
GHPModuleInvest-0.1.dist-info/METADATA
GHPModuleInvest-0.1.dist-info/WHEEL
GHPModuleInvest-0.1.dist-info/top_level.txt
GHPModuleInvest-0.1.dist-info/RECORD
