Metadata-Version: 2.1
Name: GHPModuleInvest
Version: 0.1
Summary: Uma biblioteca para cálculos de investimentos.
Home-page: https://github.com/ghpascon/meu_investimento_ghp
Author: Gabriel Henrique Pascon
Author-email: gh.pascon@gmail.com
Classifier: Programming Language :: Python :: 3
Classifier: License :: OSI Approved :: MIT License
Classifier: Operating System :: OS Independent
Requires-Python: >=3.6
License-File: LICENSE
